rollnw.cp313-win_amd64.pyd
rollnw-stubs/__init__.pyi
rollnw-stubs/kernel.pyi
rollnw-stubs/model.pyi
rollnw-stubs/nwn1.pyi
rollnw-stubs/script.pyi
rollnw-0.45.0.dist-info/LICENSE
rollnw-0.45.0.dist-info/METADATA
rollnw-0.45.0.dist-info/WHEEL
rollnw-0.45.0.dist-info/top_level.txt
rollnw-0.45.0.dist-info/RECORD
