Metadata-Version: 2.1
Name: rollnw
Version: 0.45.0
Summary: An homage to Neverwinter Nights
Author: jmd
Author-email: joshua.m.dean@gmail.com
Requires-Python: >=3.10
License-File: LICENSE
Provides-Extra: test
Requires-Dist: pytest>=6.0; extra == "test"
